setup.py
os_deferred_delete_python_novaclient_ext/__init__.py
os_deferred_delete_python_novaclient_ext.egg-info/PKG-INFO
os_deferred_delete_python_novaclient_ext.egg-info/SOURCES.txt
os_deferred_delete_python_novaclient_ext.egg-info/dependency_links.txt
os_deferred_delete_python_novaclient_ext.egg-info/requires.txt
os_deferred_delete_python_novaclient_ext.egg-info/top_level.txt