Metadata-Version: 1.0
Name: os-deferred-delete-python-novaclient-ext
Version: 0.1.0
Summary: Novaclient Extension for Instance Deferred Deletes
Home-page: https://github.com/rackspace/os_deferred_delete_python_novaclient_ext
Author: Rackspace
Author-email: rick.harris@rackspace.com
License: Apache License, Version 2.0
Platform: UNKNOWN
Classifier: Development Status :: 5 - Production/Stable
Classifier: Intended Audience :: Developers
Classifier: Intended Audience :: Information Technology
Classifier: License :: OSI Approved :: Apache Software License
Classifier: Operating System :: OS Independent
Classifier: Programming Language :: Python
